oc_distributives_mongo_api/__init__.py
oc_distributives_mongo_api/config.py
oc_distributives_mongo_api/wsgi.py
oc_distributives_mongo_api-2.2.3.dist-info/LICENSE
oc_distributives_mongo_api-2.2.3.dist-info/METADATA
oc_distributives_mongo_api-2.2.3.dist-info/WHEEL
oc_distributives_mongo_api-2.2.3.dist-info/top_level.txt
oc_distributives_mongo_api-2.2.3.dist-info/RECORD
