Metadata-Version: 2.1
Name: oc-distributives-mongo-api
Version: 2.2.3
Summary: Distributives HTTP API worker
Requires-Python: >=3.7
License-File: LICENSE
Requires-Dist: mongoengine >=0.23
Requires-Dist: Werkzeug ==2.0.3
Requires-Dist: flask ==2.0.3
Requires-Dist: gunicorn
Requires-Dist: packaging >=21.0
